[
  {
    "id": "p1",
    "title": "AARBooster",
    "organisation": "Masjid Ar-Raudhah",
    "platform": "Facebook",
    "pageUrl": "https://www.facebook.com/masjid.arraudhahsg/",
    "durationType": "short",
    "thumbnailUrl": "https://scontent.fsin9-2.fna.fbcdn.net/v/t15.5256-10/s640x640/75265055_587650391829427_7180997083380318208_n.jpg?_nc_cat=101&_nc_sid=ad6a45&_nc_ohc=9ZwqX-_ZVqsAX9Vc4wV&_nc_ht=scontent.fsin9-2.fna&_nc_tp=7&oh=dbe03ab504dd1b38712d026c79886d4c&oe=5EA190DB",
    "videos": [
      {
        "id": "v1",
        "playlistId": "p1",
        "epidsodeNumber": "e1",
        "title": "Komentar Di Facebook Tentang COVID-19",
        "videoUrl": "https://www.facebook.com/masjid.arraudhahsg/videos/2252063531563109",
        "asatizah": "Ust memeh, Ustazah memah & ustaz mimemaimeif"
      }
    ]
  },
  {
    "id": "p2",
    "title": "Hadith Online Bersama Ustaz Muhammad Idris",
    "organisation": "Masjid Ar-Raudhah",
    "platform": "Facebook",
    "pageUrl": "https://www.facebook.com/masjid.arraudhahsg/",
    "durationType": "short",
    "thumbnailUrl": "https://scontent.fsin9-1.fna.fbcdn.net/v/t15.5256-10/s640x640/71190574_2554218227966662_3080622231437443072_n.jpg?_nc_cat=107&_nc_sid=ad6a45&_nc_ohc=lAR5rfoaNPwAX8fV2dN&_nc_ht=scontent.fsin9-1.fna&_nc_tp=7&oh=20a4ff5e2c1b8b467d2500da4a974000&oe=5EA34491",
    "videos": [
      {
        "id": "v2",
        "playlistId": "p2",
        "epidsodeNumber": "e1",
        "title": "Seeing Things Positively",
        "videoUrl": "https://www.facebook.com/masjid.arraudhahsg/videos/2252063531563109",
        "asatizah": "Ust memeh, Ustazah memah & ustaz mimemaimeif"
      }
    ]
  },
  {
    "id": "p3",
    "title": "TAHSIN ONLINE bersama Imam Hanan Farihin",
    "organisation": "Masjid Ar-Raudhah",
    "platform": "Facebook",
    "pageUrl": "https://www.facebook.com/masjid.arraudhahsg/",
    "durationType": "short",
    "thumbnailUrl": "https://scontent.fsin9-2.fna.fbcdn.net/v/t15.5256-10/70697766_508976516625042_1410156965799133184_n.jpg?_nc_cat=109&_nc_sid=ad6a45&_nc_ohc=Z4uwopmahGYAX8tVi6W&_nc_ht=scontent.fsin9-2.fna&oh=5b2c94c7dfe9f1e9e7d62ba6444414cd&oe=5EA30281",
    "videos": [
      {
        "id": "v3",
        "playlistId": "p3",
        "epidsodeNumber": "e1",
        "title": "Salah kau lah ni!",
        "videoUrl": "https://www.facebook.com/masjid.arraudhahsg/videos/2252063531563109",
        "asatizah": "Ust memeh, Ustazah memah & ustaz mimemaimeif"
      },
      {
        "id": "v4",
        "playlistId": "p3",
        "epidsodeNumber": "e2",
        "title": "Komentar Di Facebook Tentang COVID-20",
        "videoUrl": "https://www.facebook.com/masjid.arraudhahsg/videos/2252063531563109",
        "asatizah": "Ust memeh, Ustazah memah & ustaz mimemaimeif"
      },
      {
        "id": "v5",
        "playlistId": "p3",
        "epidsodeNumber": "e3",
        "title": "Seeing Things Positively",
        "videoUrl": "https://www.facebook.com/masjid.arraudhahsg/videos/2252063531563109",
        "asatizah": "Ust memeh, Ustazah memah & ustaz mimemaimeif"
      }
    ]
  },
  {
    "id": "p4",
    "title": "#ARRQuranReflections Bersama Imam Hanan Farihin",
    "organisation": "Masjid Ar-Raudhah",
    "platform": "Facebook",
    "pageUrl": "https://www.facebook.com/masjid.arraudhahsg/",
    "durationType": "short",
    "thumbnailUrl": "https://scontent.fsin9-1.fna.fbcdn.net/v/t15.5256-10/s640x640/72792015_1019491541734121_4367033033295921152_n.jpg?_nc_cat=105&_nc_sid=ad6a45&_nc_ohc=Zjr1PGwrpAAAX8J5uwV&_nc_ht=scontent.fsin9-1.fna&_nc_tp=7&oh=c7ecbbca7099134f7660ead4fc1a30e6&oe=5EA39B99",
    "videos": [
      {
        "id": "v6",
        "playlistId": "p4",
        "epidsodeNumber": "e1",
        "title": "Salah kau lah ni!",
        "videoUrl": "https://www.facebook.com/masjid.arraudhahsg/videos/2252063531563109",
        "asatizah": "Ust memeh, Ustazah memah & ustaz mimemaimeif"
      },
      {
        "id": "v7",
        "playlistId": "p4",
        "epidsodeNumber": "e2",
        "title": "Komentar Di Facebook Tentang COVID-21",
        "videoUrl": "https://www.facebook.com/masjid.arraudhahsg/videos/2252063531563109",
        "asatizah": "Ust memeh, Ustazah memah & ustaz mimemaimeif"
      },
      {
        "id": "v8",
        "playlistId": "p4",
        "epidsodeNumber": "e3",
        "title": "Seeing Things Positively",
        "videoUrl": "https://www.facebook.com/masjid.arraudhahsg/videos/2252063531563109",
        "asatizah": "Ust memeh, Ustazah memah & ustaz mimemaimeif"
      },
      {
        "id": "v9",
        "playlistId": "p4",
        "epidsodeNumber": "e4",
        "title": "Salah kau lah ni!",
        "videoUrl": "https://www.facebook.com/masjid.arraudhahsg/videos/2252063531563109",
        "asatizah": "Ust memeh, Ustazah memah & ustaz mimemaimeif"
      }
    ]
  }
]
